{
  "kind": "collectionType",
  "collectionName": "card_serviss",
  "info": {
    "singularName": "card-servis",
    "pluralName": "card-serviss",
    "displayName": "CardServis",
    "description": ""
  },
  "options": {
    "draftAndPublish": true
  },
  "pluginOptions": {},
  "attributes": {
    "CardImg": {
      "type": "media",
      "multiple": false,
      "required": true,
      "allowedTypes": [
        "images",
        "files",
        "videos",
        "audios"
      ]
    },
    "CardHead": {
      "type": "string"
    },
    "CardText": {
      "type": "text"
    },
    "CardUrl": {
      "type": "string"
    },
    "imageUrl": {
      "type": "string"
    }
  }
}
